{
  "school": [
    {
      "name": "Anthem",
      "listName": "anthem",
      "id": 1,
      "abbr": "an",
      "path": "/an/Slider/wowslider.html"
    },
    {
      "name": "Magma Ranch",
      "listName": "magma",
      "id": 2,
      "abbr": "mg",
      "path": "/mg/Slider/wowslider.html"
    },
    {
      "name": "Florence",
      "listName": "florencek8",
      "id": 3,
      "abbr": "fk8",
      "path": "/fk8/Slider/wowslider.html"
    },
    {
      "name": "Walker Butte",
      "listName": "walkerbutte",
      "id": 4,
      "abbr": "wb",
      "path": "/wb/Slider/wowslider.html"
    },
    {
      "name": "Circle Cross Ranch",
      "listName": "circlecross",
      "id": 5,
      "abbr": "ccr",
      "path": "/ccr/Slider/wowslider.html"
    },
    {
      "name": "Skyline Ranch",
      "listName": "skyline",
      "id": 6,
      "abbr": "sr",
      "path": "/sr/Slider/wowslider.html"
    },
    {
      "name": "Copper Basin",
      "listName": "copperbasin",
      "id": 7,
      "abbr": "cb",
      "path": "/cb/Slider/wowslider.html"
    },
    {
      "name": "San Tan Foothills",
      "listName": "santanfoothills",
      "id": 8,
      "abbr": "stfhs",
      "path": "/stfhs/Slider/wowslider.html"
    },
    {
      "name": "San Tan Heights",
      "listName": "santanheights",
      "id": 9,
      "abbr": "sth",
      "path": "/sth/Slider/wowslider.html"
    },
    {
      "name": "Poston Butte",
      "listName": "postonbutte",
      "id": 10,
      "abbr": "pbhs",
      "path": "/pbhs/Slider/wowslider.html"
    },
    {
      "name": "Florence High",
      "listName": "florencehigh",
      "id": 11,
      "abbr": "fhs",
      "path": "/fhs/Slider/wowslider.html"
    }
  ]
}
